{"text": "第8章知识问答丁力海知智能，杨成彪南京柯基数据科技有限公司知识问答通过自然语言对话的形式帮助人们从知识库中获取知识，它不但是知识图谱的核心应用之一，也是自然语言处理的重要研究方向。", "relation": [{"head": "知识问答", "head_type": "概念 ", "relation": "被定义为", "tail": "过自然语言对话的形式帮助人们从知识库中获取知识", "tail_type": "概念 "}]}
{"text": "8.1知识问答概述知识问答系统是一个拟人化的智能系统，它接收使用自然语言表达的问题，理解用户的意图，获取相关的知识，最终通过推理计算形成自然语言表达的答案并反馈给用户。", "relation": [{"head": "知识问答系统", "head_type": "概念", "relation": "被定义为", "tail": "智能拟人系统", "tail_type": "概念"}]}
{"text": "8.1.1知识问答的基本要素知识问答或问答（Question_Answering,QA）是对话的一种形态。", "relation": [{"head": "知识问答或问答", "head_type": "概念", "relation": "英文名", "tail": "Question_Answering,QA", "tail_type": "概念"}]}
{"text": "问答是一种典型的智能行为，例如著名的图灵测试就是考验能否通过自然语言对话的方式判定答题者是人还是机器。", "relation": [{"head": "问答", "head_type": "", "relation": "属于", "tail": "智能行为", "tail_type": ""}]}
{"text": "图8-1问答系统的四大要素8.1.2知识问答的相关工作信息检索（Information_Retrieval,IR）或搜索以关键词搜索为代表，帮助用户发现包含搜索关键词的网页或文档。", "relation": [{"head": "信息检索（Information_Retrieval,IR）", "head_type": "概念", "relation": "实现", "tail": "概念", "tail_type": "帮助用户发现包含搜索关键词的网页或文档"}]}
{"text": "数据库查询（Database_Query）同样可以帮助用户获取知识，但是知识问答和数据库查询仍然存在一定差异。", "relation": [{"head": "数据库查询", "head_type": "概念", "relation": "英文名", "tail": "Database_Query", "tail_type": "概念"}]}
{"text": "图8-2“沃森”在《危险边缘》中获得冠军图8-3问答展示界面案例2.知识问答技术可以应用于智能对话系统、智能客服或智能助理（IntelligentAgent）[7]。", "relation": [{"head": "知识问答技术", "head_type": "概念", "relation": "实现", "tail": "智能对话系统、智能客服或智能助理", "tail_type": "概念"}]}
{"text": "事实型问题是知识问答中处理频度较高的一种问题类型，其中包含了谓词型问题（答案是一个单一的对象）、列表型问题（返回的不止一个答案，而是一列答案）。", "relation": [{"head": "事实型问题类型", "head_type": "概念", "relation": "包含", "tail": "谓词型问题", "tail_type": "概念"}, {"head": "事实型问题类型", "head_type": "概念", "relation": "包含", "tail": "列表型问题", "tail_type": "概念"}]}
{"text": "开放域问答系统经常使用万维网数据（尤其是百科网站、社区问答等）作为数据源解答用户的问题。", "relation": [{"head": "开放问答系统", "head_type": "概念", "relation": "依靠", "tail": "万维网数据", "tail_type": "产品"}]}
{"text": "电子表格、二维表或者关系数据库是最常见的结构化知识，实体和属性通过简单的二维表表示，大多数事实性客观问题都可以被此类知识解答。", "relation": [{"head": "电子表格", "head_type": "概念", "relation": "属于", "tail": "结构化知识", "tail_type": "概念"}, {"head": "二维表", "head_type": "概念", "relation": "属于", "tail": "结构化知识", "tail_type": "概念"}]}
{"text": "图数据库，例如RDF、属性图、语义网络等，将通过节点、有向边来形成基于图的知识组织，并且利用节点和边的名称与上下文对接自然语言处理并支持语义相似度计算，同时还能支持复杂的结构化图查询机制。", "relation": [{"head": "图数据库", "head_type": "概念", "relation": "实现", "tail": "基于图的知识组织", "tail_type": "功能"}, {"head": "图数据库", "head_type": "概念", "relation": "实现", "tail": "语义相似度计算", "tail_type": "功能"}, {"head": "图数据库", "head_type": "概念", "relation": "实现", "tail": "查询机制", "tail_type": "功能"}]}
{"text": "根据知识库表示形式的不同，目前的知识问答可以分为传统问答方法（符号表示）以及基于深度学习的问答方法（分布式表示）两种类型。", "relation": [{"head": "问答方法", "head_type": "概念", "relation": "包含", "tail": "传统问答方法", "tail_type": "概念"}, {"head": "问答方法", "head_type": "概念", "relation": "包含", "tail": "基于深度学习的问答方法", "tail_type": "概念"}]}
{"text": "基于模式匹配的语义理解可以直接将问题映射到查询。", "relation": [{"head": "基于模式匹配的语义理解", "head_type": "概念", "relation": "实现", "tail": "问题映射到查询", "tail_type": ""}]}
{"text": "这一类方案后来演进为KBQA中基于语义解析（Semantic_Parsing）的语义理解方法。", "relation": [{"head": "语义解析", "head_type": "概念", "relation": "英文名", "tail": "Semantic_Parsing", "tail_type": "概念"}]}
{"text": "图8-13IRQA的基本架构 [13]8.3.3KBQA：基于知识库的问答系统基于知识库的问答系统（Knowledge-Based_Question_Answering,KBQA)特指使用基于知识图谱解答问题的问答系统。", "relation": [{"head": "基于知识库的问答系统", "head_type": "概念", "relation": "等价", "tail": "基于知识图谱解答问题的问答系统", "tail_type": "概念"}]}
{"text": "常用的问答指标采用F1（综合正确率和召回率）和P@1（第一个答案是否正确的比率）。", "relation": [{"head": "问答指标", "head_type": "概念", "relation": "包含", "tail": "F1", "tail_type": "概念"}, {"head": "问答指标", "head_type": "概念", "relation": "包含", "tail": "P@1", "tail_type": "概念"}]}
{"text": "QALD的主要任务如下：给定知识库（一个或多个RDF数据集以及其他知识源）和问题（自然语言问题或关键字），返回正确的答案或返回这些答案的SPARQL查询。", "relation": [{"head": "QALD", "head_type": "概念", "relation": "研究", "tail": "给定知识库（一个或多个RDF数据集以及其他知识源）和问题（自然语言问题或关键字），返回正确的答案或返回这些答案的SPARQL查询", "tail_type": "概念"}]}
{"text": "对于Resources和Classes，实体识别的常用方法主要有两点，一是用WordNet定义知识库中标签的同义词，二是计算字符串间的相似度。", "relation": [{"head": "实体识别常用方法", "head_type": "概念", "relation": "包含", "tail": "WordNet定义知识库中标签的同义词", "tail_type": "概念"},{"head": "实体识别常用方法", "head_type": "概念", "relation": "包含", "tail": "计算字符串间相似度", "tail_type": "概念"}]}
